python_tools_mcp/__init__.py
python_tools_mcp/server.py
python_tools_mcp-0.2.0.dist-info/METADATA
python_tools_mcp-0.2.0.dist-info/WHEEL
python_tools_mcp-0.2.0.dist-info/entry_points.txt
python_tools_mcp-0.2.0.dist-info/licenses/LICENSE
python_tools_mcp-0.2.0.dist-info/RECORD
