Metadata-Version: 2.4
Name: python-tools-mcp
Version: 0.2.0
Summary: Python development tools as an MCP
Project-URL: Homepage, https://github.com/benfjensen/python_tools_mcp
Project-URL: Bug Tracker, https://github.com/benfjensen/python_tools_mcp/issues
Author-email: Ben O'Mahony <ben@benomahony.com>
License: MIT
License-File: LICENSE
Classifier: Development Status :: 4 - Beta
Classifier: Intended Audience :: Developers
Classifier: License :: OSI Approved :: MIT License
Classifier: Programming Language :: Python :: 3
Classifier: Programming Language :: Python :: 3.11
Classifier: Programming Language :: Python :: 3.12
Classifier: Topic :: Software Development :: Libraries :: Python Modules
Requires-Python: >=3.11
Requires-Dist: mcp>=1.9.3
Requires-Dist: pydantic>=2.11.5
Requires-Dist: uv>=0.1.19
